aem_instance_manager/__init__.py
aem_instance_manager/main.py
aem_instance_manager-0.6.dist-info/licenses/LICENSE
aem_instance_manager-0.6.dist-info/METADATA
aem_instance_manager-0.6.dist-info/WHEEL
aem_instance_manager-0.6.dist-info/entry_points.txt
aem_instance_manager-0.6.dist-info/top_level.txt
aem_instance_manager-0.6.dist-info/RECORD
