Metadata-Version: 2.4
Name: aem_instance_manager
Version: 0.6
Summary: An AEM instance management tool designed to simplify switching across multiple project environments.
Home-page: https://github.com/mayursatav/aem-instance-manager
Author: Mayur Satav
Author-email: mayursatav9@gmail.com
Classifier: Programming Language :: Python :: 3
Classifier: License :: OSI Approved :: MIT License
Classifier: Operating System :: OS Independent
Requires-Python: >=3.6
License-File: LICENSE
Requires-Dist: pandas
Dynamic: author
Dynamic: author-email
Dynamic: classifier
Dynamic: description
Dynamic: description-content-type
Dynamic: home-page
Dynamic: license-file
Dynamic: requires-dist
Dynamic: requires-python
Dynamic: summary
